<?xml version="1.0" encoding="utf-8" ?>
<dwsync>
<file name="dialog.css" server="123.30.181.125/public_html/demo/" local="129585692962973576" remote="129592524000000000" />
<file name="editor.css" server="123.30.181.125/public_html/demo/" local="129585692963083582" remote="129592524000000000" />
<file name="elementspath.css" server="123.30.181.125/public_html/demo/" local="129585692958613326" remote="129592524000000000" />
<file name="icons.css" server="123.30.181.125/public_html/demo/" local="129585692958523321" remote="129592524000000000" />
<file name="icons.png" server="123.30.181.125/public_html/demo/" local="129585692959233362" remote="129592524000000000" />
<file name="icons_rtl.png" server="123.30.181.125/public_html/demo/" local="129585692953533036" remote="129592524000000000" />
<file name="mainui.css" server="123.30.181.125/public_html/demo/" local="129585692957333253" remote="129592524000000000" />
<file name="menu.css" server="123.30.181.125/public_html/demo/" local="129585692953483033" remote="129592524000000000" />
<file name="panel.css" server="123.30.181.125/public_html/demo/" local="129585692954803109" remote="129592524000000000" />
<file name="presets.css" server="123.30.181.125/public_html/demo/" local="129585692954683102" remote="129592524000000000" />
<file name="reset.css" server="123.30.181.125/public_html/demo/" local="129585692956953232" remote="129592524000000000" />
<file name="richcombo.css" server="123.30.181.125/public_html/demo/" local="129585692953333024" remote="129592524000000000" />
<file name="skin.js" server="123.30.181.125/public_html/demo/" local="129585692953283022" remote="129592524000000000" />
<file name="templates.css" server="123.30.181.125/public_html/demo/" local="129585692953123012" remote="129592524000000000" />
<file name="toolbar.css" server="123.30.181.125/public_html/demo/" local="129585692952983004" remote="129592524000000000" />
</dwsync>